<?xml version="1.0" encoding="UTF-8"?>
<objects serializationModel="Studio.02.01.00">
	<object class="AudioFile" id="{37330415-dd62-4526-80e2-33cdc7c5abf8}">
		<property name="assetPath">
			<value>Wisper1.wav</value>
		</property>
		<property name="frequencyInKHz">
			<value>44.0999985</value>
		</property>
		<property name="channelCount">
			<value>1</value>
		</property>
		<property name="length">
			<value>3.2275736961451247</value>
		</property>
		<relationship name="masterAssetFolder">
			<destination>{52cf734a-3020-4c80-b899-e08a100fcf9f}</destination>
		</relationship>
	</object>
</objects>
